{
  "$schema": "https://sethmay.github.io/open-scout-api/schema/v1/camp.schema.json",
  "id": "ca-camp-trask-cub-twilight-camp",
  "kind": "camp",
  "versions": [
    {
      "valid_from": null,
      "valid_to": null,
      "name": "Camp Trask (Cub Twilight Camp)",
      "camp_type": "day_camp",
      "operator": "council",
      "council": "council:greater-los-angeles-area",
      "parent": null,
      "operating_status": "active",
      "address": "1100 N Canyon Blvd",
      "city": "Monrovia",
      "state": "CA",
      "lat": 34.1747955,
      "lon": -117.9880102,
      "geo_precision": "exact",
      "elevation_ft": 1280,
      "website": "https://greaterlascouting.org/camp-trask/",
      "program_types": [
        "cub_day"
      ],
      "features": [],
      "summary": "Cub Scout twilight day camp at the Greater Los Angeles Area Council's Trask Scout Reservation in Monrovia Canyon Park, offering advancement-focused activities including BB and target sports, archery, a swimming pool, a historic fort, and campfire programs.",
      "provenance": {
        "sources": [
          {
            "citation": "camp-finder council-033/ca-camp-trask-cub-twilight-camp (unofficial community dataset)"
          },
          {
            "url": "https://greaterlascouting.org/camp-trask/"
          },
          {
            "url": "https://greaterlascouting.org/camp-trask/"
          }
        ],
        "method": "imported",
        "verified_at": "2026-07-17",
        "imported_at": "2026-07-21",
        "confidence": 0.6,
        "notes": "Imported from camp-finder; raw description and sessions dropped (operational data stays at the council site). verified_at is camp-finder's own source-confirmation date; imported_at is when open-scout-api ingested it. The evergreen summary is original prose regenerated from that description, excluding dates/fees/schedules. camp_type classified from program_types."
      }
    }
  ],
  "notes": null
}
