{
  "id": "il-saukenauk-scout-reservation-webelos-and-arrow-of-light-adventure-camp",
  "kind": "camp",
  "versions": [
    {
      "valid_from": null,
      "valid_to": null,
      "name": "Saukenauk Scout Reservation - Webelos & Arrow of Light Adventure Camp",
      "camp_type": "resident_camp",
      "operator": "council",
      "council": "council:mississippi-valley",
      "parent": null,
      "operating_status": "active",
      "address": "2948 E 1000th St",
      "city": "Mendon",
      "state": "IL",
      "lat": 40.1885197,
      "lon": -91.3208037,
      "website": "https://mvcscouting.org/camping/",
      "program_types": [
        "webelos"
      ],
      "features": [],
      "provenance": {
        "sources": [
          {
            "citation": "camp-finder council-141/il-saukenauk-scout-reservation-webelos-and-arrow-of-light-adventure-camp (unofficial community dataset)"
          },
          {
            "url": "https://mvcscouting.org/camping/"
          },
          {
            "url": "https://mvcscouting.org/camping/"
          }
        ],
        "method": "imported",
        "verified_at": "2026-07-21",
        "confidence": 0.6,
        "notes": "Imported from camp-finder; description/sessions dropped (operational data stays at the council site). camp_type classified from program_types."
      }
    }
  ],
  "notes": null
}
